pyTape/__init__.py
pyTape/pyTape.py
pyTape-0.0.6.dist-info/METADATA
pyTape-0.0.6.dist-info/WHEEL
pyTape-0.0.6.dist-info/top_level.txt
pyTape-0.0.6.dist-info/RECORD
