Metadata-Version: 2.1
Name: pyTape
Version: 0.0.6
Summary: Tape
Home-page: https://github.com/kawaai-hina/pyTape
Author: kawaai-hina
Author-email: kawaai@qq.com
License: UNKNOWN
Platform: UNKNOWN
Classifier: Programming Language :: Python :: 3
Classifier: Operating System :: OS Independent
Requires-Python: >=3.6
